# Save the game opening and result to disk?
# Setting to `True` allows Ares to select a new opening after defeat
UseData: False
# How should we choose a build? Cycle is the only option for now
BuildSelection: Cycle
# For each Race / Opponent ID choose a build selection
BuildChoices:
    test_123:
        BotName: Test
        Cycle:
            - B2GM_Starting_Build_PVZ
    Protoss:
        BotName: ProtossRace
        Cycle:
            - B2GM_PVP-2_Gate_Expand
    Terran:
        BotName: TerranRace
        Cycle:
            - B2GM_Starting_Build
    Zerg:
        BotName: ZergRace
        Cycle:
            - B2GM_Starting_Build_PVZ
    Random:
        BotName: RandomRace
        Cycle:
            - B2GM_Starting_Build

    # Can also use specific opponent ids (overrides race options above)
    a_bot_opponent_id_from_aiarena:
        BotName: test
        Cycle:
            - B2GM_Starting_Build

Builds:
    B2GM_Starting_Build:
        # Build constant worker production till this supply
        ConstantWorkerProductionTill: 44
        # After 0 supply turn AutoSupply on
        AutoSupplyAtSupply: 33
        OpeningBuildOrder:
            - 14 PYLON @ nat_wall
            - 16 GATEWAY @ nat_wall
            - 16 CHRONO @ NEXUS
            - 16 WORKER_SCOUT:
                [enemy_spawn, enemy_nat, map_center, fourth,third, enemy_nat,spawn,nat,]
            - 16 GAS
            - 20 EXPAND
            - 20 CORE @ nat_wall
            - 21 PYLON
            - 21 GAS
            - 22 WARPGATERESEARCH
            - 22 CHRONO @ NEXUS # chroning instead of cyber
            - 24 STALKER
            - 26 CHRONO @ GATEWAY
            - 26 ROBOTICSFACILITY
            - 27 STALKER
            - 27 CHRONO @ NEXUS #Chrono Gateway if PVP instead of NEXUS
            - 28 GATEWAY @ nat_wall
            - 28 GATEWAY 
            - 30 STALKER
            - 33 CHRONO @ NEXUS
            - 34 PYLON @ nat_wall
            - 34 OBSERVER
            - 35 GAS x2
            - 40 IMMORTAL
            - 40 CHRONO @  ROBOTICSFACILITY
            - 48 STALKER *3 @ NAT
            - 50 ROBOTICSBAY
            - 50 ROBOTICSFACILITY
            - 52 IMMORTAL
            - 54 EXPAND
            - 55 COLOSSUS x2
            - 55 CHRONO @ ROBOTICSFACILITY x2
            - 56 EXTENDEDTHERMALLANCE
            - 56 TWILIGHTCOUNCIL
            - 56 FORGE
            - 57 CHRONO @ ROBOTICSBAY
            - 58 GAS x2
            - 58 PROTOSSGROUNDARMORSLEVEL1
            - 58 CHARGE
            - 59 CHRONO @ FORGE
            - 59 DISRUPTOR
            - 59 CHRONO @ TWILIGHTCOUNCIL 
            - 62 GATEWAY 
            - 62 GATEWAY
            - 62 GATEWAY
            - 62 GATEWAY
            - 62 GATEWAY
            - 62 TEMPLARARCHIVE
            - 63 CHRONO @ FORGE
            - 64 WARPPRISM
            - 64 DISRUPTOR
            - 66 HIGHTEMPLAR *4 @ NAT
            - 66 ZEALOT *2 @ NAT

    B2GM_Starting_Build_PVZ:
        # Build constant worker production till this supply
        ConstantWorkerProductionTill: 44
        # After 0 supply turn AutoSupply on
        AutoSupplyAtSupply: 33
        OpeningBuildOrder:
            - 14 PYLON @ nat_wall
            - 16 GATEWAY @ nat_wall
            - 16 CHRONO @ NEXUS
            - 16 WORKER_SCOUT:
                [enemy_spawn, enemy_nat, map_center, fourth,third, enemy_nat]
            - 16 GAS
            - 20 EXPAND
            - 20 CORE @ nat_wall
            - 21 PYLON
            - 21 GAS
            - 22 WARPGATERESEARCH
            - 22 CHRONO @ NEXUS # chroning instead of cyber
            - 24 ZEALOT
            - 26 CHRONO @ GATEWAY
            - 26 ROBOTICSFACILITY
            - 27 STALKER
            - 27 CHRONO @ NEXUS 
            - 27 GATEWAY @ nat_wall
            - 28 GATEWAY 
            - 30 STALKER
            - 33 CHRONO @ NEXUS
            - 34 PYLON @ nat_wall
            - 34 OBSERVER
            - 35 GAS x2
            - 36 IMMORTAL
            - 36 CHRONO @  ROBOTICSFACILITY
            - 48 STALKER *3 @ NAT
            - 50 ROBOTICSBAY
            - 50 ROBOTICSFACILITY
            - 52 IMMORTAL x2
            - 54 EXPAND
            - 55 COLOSSUS x2
            - 55 CHRONO @ ROBOTICSFACILITY x2
            - 56 EXTENDEDTHERMALLANCE
            - 56 TWILIGHTCOUNCIL
            - 56 FORGE
            - 57 CHRONO @ ROBOTICSBAY
            - 58 GAS x2
            - 58 PROTOSSGROUNDARMORSLEVEL1
            - 58 CHARGE
            - 59 CHRONO @ FORGE
            - 59 DISRUPTOR x2
            - 59 CHRONO @ TWILIGHTCOUNCIL 
            - 62 GATEWAY 
            - 62 GATEWAY
            - 62 GATEWAY
            - 62 GATEWAY
            - 62 GATEWAY
            - 62 TEMPLARARCHIVE
            - 63 CHRONO @ FORGE
            - 64 WARPPRISM
            - 64 IMMORTAL
            - 66 HIGHTEMPLAR *4 @ NAT
            - 66 ZEALOT *2 @ NAT
    B2GM_PVP-2_Gate_Expand:
        # Build constant worker production till this supply
        ConstantWorkerProductionTill: 44
        # After 0 supply turn AutoSupply on
        AutoSupplyAtSupply: 21
        OpeningBuildOrder:
            - 14 PYLON @ ramp
            - 16 GATEWAY 
            - 16 CHRONO @ NEXUS
            - 16 WORKER_SCOUT:
                [enemy_spawn, enemy_nat, map_center, fourth,third, enemy_nat]
            - 17 GAS
            - 18 GAS
            - 19 GATEWAY @ ramp
            - 20 CORE @ ramp
            - 21 PYLON @ NAT
            - 22 WARPGATERESEARCH
            - 22 STALKER x2
            - 22 CHRONO @ NEXUS 
            - 27 EXPAND
            - 27 SENTRY x2
            - 32 ROBOTICSFACILITY
            - 33 SHIELDBATTERY @ NAT
            - 35 STALKER x2
            - 40 OBSERVER
            - 49 STALKER
            - 51 STALKER
            - 52 ROBOTICSBAY
            - 52 TWILIGHTCOUNCIL #temporary until produciton controller is fixed
            - 54 STALKER x2
            - 55 GAS
            - 55 GAS
            - 54 STALKER
            - 54 STALKER
            - 56 ROBOTICSFACILITY
            - 56 TEMPLARARCHIVE #temporary until production controller is fixed
            - 56 EXTENDEDTHERMALLANCE
            
            
    
    
    B2GM_PVP_4-Gate_ALL-IN:
        # Build constant worker production till this supply
        ConstantWorkerProductionTill: 44
        # After 0 supply turn AutoSupply on
        AutoSupplyAtSupply: 33
        OpeningBuildOrder:
            - 14 PYLON @ ramp
            - 14 CHRONO @ NEXUS
            - 16 GATEWAY
            - 16 WORKER_SCOUT:
                [enemy_spawn, enemy_nat, map_center, fourth,third, enemy_nat]
            - 16 GAS
            - 18 GAS
            - 19 GATEWAY @ ramp
            - 20 CORE @ ramp
            - 21 PYLON
            - 22 WARPGATERESEARCH
            - 22 CHRONO @ NEXUS 
            - 23 Pylon @nat_wall
            - 24 STALKER x2
            - 26 CHRONO @ GATEWAY
            - 26 CHRONO @ GATEWAY
            - 27 GATEWAY @ nat_wall 
            

    One_Base_Reaction_Build:
        # One base reaction Build order
        ConstantWorkerProductionTill: 44
        AutoSupplyAtSupply: 0
        OpeningBuildOrder:
            - 14 PYLON
            - 16 GATEWAY @ nat_wall
            - 16 CHRONO @ GATEWAY
            - 20 STALKER *3
            - 20 SHIELDBATTERY @ nat_wall
            - 24 SHIELDBATTERY 
            - 24 PYLON @ nat_wall

    Cheese_Reaction_Build:
        # Chesese reaction Build order
        ConstantWorkerProductionTill: 20
        AutoSupplyAtSupply: 0
        OpeningBuildOrder:
            - 20 PYLON @ nat_wall
            - 20 GATEWAY @ nat_wall
            - 20 CORE @ nat_wall
            - 20 ZEALOT
            - 22 SHIELDBATTERY @ nat_wall
            - 22 ZEALOT
            - 24 PYLON @ nat_wall
            - 24 GATEWAY @ nat_wall
            - 24 WARPGATERESEARCH
            - 24 PYLON @ nat_wall
            - 24 CHRONO @ GATEWAY
        
